LICENSE
README.md
setup.py
src/rMETL/__init__.py
src/rMETL/rMETL
src/rMETL/rMETL_MEIcalling.py
src/rMETL/rMETL_cmdRunner.py
src/rMETL/rMETL_concensus.py
src/rMETL/rMETL_extraction.py
src/rMETL/rMETL_genotype.py
src/rMETL/rMETL_realign.py
src/rMETL/rMETL_utils.py
src/rMETL/rMETL_version.py
src/rMETL.egg-info/PKG-INFO
src/rMETL.egg-info/SOURCES.txt
src/rMETL.egg-info/dependency_links.txt
src/rMETL.egg-info/not-zip-safe
src/rMETL.egg-info/requires.txt
src/rMETL.egg-info/top_level.txt