Metadata-Version: 1.0
Name: rMETL
Version: 1.0.4
Summary: realignment-based Mobile Element insertion detection Tool for Long read
Home-page: https://github.com/tjiangHIT/rMETL
Author: Jiang Tao
Author-email: tjiang@hit.edu.cn
License: MIT
Platform: UNKNOWN
